{"version": 0.6, "generator": "Overpass API 0.7.62.7 375dc00a", "osm3s": {"timestamp_osm_base": "2025-06-27T21:33:16Z", "copyright": "The data included in this document is from www.openstreetmap.org. The data is made available under ODbL."}, "elements": [{"type": "node", "id": 150938564, "lat": 44.3976247, "lon": -122.736195, "tags": {"ele": "161", "gnis:feature_id": "1127827", "name": "Sweet Home", "place": "town", "population": "8576", "population:date": "2006", "source:population": "US Census", "wikidata": "Q994957", "wikipedia": "en:Sweet Home, Oregon"}}]}